sku/__init__.py
sku/models.py
sku/parser.py
sku/schema.py
tf2_sku_to_name-2.0.4.dist-info/licenses/LICENSE
tf2_sku_to_name-2.0.4.dist-info/METADATA
tf2_sku_to_name-2.0.4.dist-info/WHEEL
tf2_sku_to_name-2.0.4.dist-info/top_level.txt
tf2_sku_to_name-2.0.4.dist-info/RECORD
